llm_cli/__init__.py
llm_cli/cli.py
llm_cli/config.py
llm_cli/execute.py
llm_cli/prompt.py
llm_cli/query.py
llm_cli/providers/__init__.py
llm_cli/providers/anthropic.py
llm_cli/providers/base.py
llm_cli/providers/deepseek.py
llm_cli/providers/gemini.py
llm_cli/providers/minimax.py
llm_cli/providers/moonshot.py
llm_cli/providers/openai.py
llm_cli/providers/openrouter.py
llm_cli/providers/sambanova.py
llm_cli/providers/siliconflow.py
llm_cli/providers/tencent.py
llm_cli/tools/__init__.py
llm_cli/tools/calculator.py
llm_cli/tools/decorators.py
llm_cli/tools/file.py
llm_cli/tools/history.py
llm_cli/tools/replace.py
llm_cli/utils/markdown_renderer.py
llm_clients-0.1.0.dist-info/METADATA
llm_clients-0.1.0.dist-info/WHEEL
llm_clients-0.1.0.dist-info/entry_points.txt
llm_clients-0.1.0.dist-info/licenses/LICENSE
llm_clients-0.1.0.dist-info/RECORD
