Metadata-Version: 2.4
Name: llm-clients
Version: 0.1.0
Summary: UNIX-style command line utilities for working with Large Language Models
Author-email: PsychArch <psycharch@github.com>
License-Expression: MIT
License-File: LICENSE
Keywords: ai,clients,llm,prompt,tools,unix
Classifier: Development Status :: 3 - Alpha
Classifier: Environment :: Console
Classifier: Intended Audience :: Developers
Classifier: License :: OSI Approved :: MIT License
Classifier: Programming Language :: Python :: 3
Classifier: Programming Language :: Python :: 3.8
Classifier: Programming Language :: Python :: 3.9
Classifier: Programming Language :: Python :: 3.10
Classifier: Programming Language :: Python :: 3.11
Classifier: Topic :: Utilities
Requires-Python: >=3.8
Requires-Dist: aiohttp>=3.8.0
Requires-Dist: anthropic>=0.5.0
Requires-Dist: click>=8.0.0
Requires-Dist: google-genai
Requires-Dist: openai>=1.0.0
Requires-Dist: pyyaml>=6.0.0
Requires-Dist: rich>=13.0.0
Requires-Dist: tencentcloud-sdk-python-common>=3.0.1000
Requires-Dist: tencentcloud-sdk-python-lkeap>=3.0.1000
Requires-Dist: tencentcloud-sdk-python>=3.0.1000
Requires-Dist: xmltodict>=0.13.0
Provides-Extra: dev
Requires-Dist: pytest-asyncio>=0.23.0; extra == 'dev'
Requires-Dist: pytest>=7.0.0; extra == 'dev'
